{
  "version": "7",
  "dialect": "postgresql",
  "entries": [
    {
      "idx": 0,
      "version": "7",
      "when": 1776449595530,
      "tag": "0000_pale_pet_avengers",
      "breakpoints": true
    },
    {
      "idx": 1,
      "version": "7",
      "when": 1776449829867,
      "tag": "0001_strange_thunderbolt",
      "breakpoints": true
    },
    {
      "idx": 2,
      "version": "7",
      "when": 1776450345840,
      "tag": "0002_cloudy_madripoor",
      "breakpoints": true
    },
    {
      "idx": 3,
      "version": "7",
      "when": 1776450556055,
      "tag": "0003_curly_wonder_man",
      "breakpoints": true
    },
    {
      "idx": 4,
      "version": "7",
      "when": 1776523760524,
      "tag": "0004_wakeful_wither",
      "breakpoints": true
    },
    {
      "idx": 5,
      "version": "7",
      "when": 1776531367736,
      "tag": "0005_busy_may_parker",
      "breakpoints": true
    }
  ]
}